lambda_local/__init__.py
lambda_local/lambda_local.py
lambda_local/test/__init__.py
lambda_local/test/lambda_local_test.py
lambda_local-1.0.0.dist-info/METADATA
lambda_local-1.0.0.dist-info/WHEEL
lambda_local-1.0.0.dist-info/top_level.txt
lambda_local-1.0.0.dist-info/RECORD
