Metadata-Version: 2.1
Name: lambda-local
Version: 1.0.0
Summary: A AWS Lambda Running In Local package.
Home-page: https://github.com/AbhimanyuHK/Lambda_Local
Author: Abhimanyu HK
Author-email: manyu1994@hotmail.com
License: UNKNOWN
Platform: UNKNOWN
Classifier: Programming Language :: Python :: 3
Classifier: Programming Language :: Python :: 2
Classifier: License :: OSI Approved :: MIT License
Classifier: Operating System :: OS Independent
